selection/__init__.py
selection/data/__init__.py
selection/data/utils.py
selection/layers/__init__.py
selection/layers/concrete_gates.py
selection/layers/concrete_mask.py
selection/layers/concrete_mask_conv.py
selection/layers/concrete_max.py
selection/layers/concrete_new.py
selection/layers/concrete_selector.py
selection/layers/utils.py
selection/models/__init__.py
selection/models/mlp.py
selection/models/train.py
selection/models/utils.py
dl_selection-0.0.3.dist-info/LICENSE
dl_selection-0.0.3.dist-info/METADATA
dl_selection-0.0.3.dist-info/WHEEL
dl_selection-0.0.3.dist-info/top_level.txt
dl_selection-0.0.3.dist-info/RECORD
