Metadata-Version: 2.1
Name: dl-selection
Version: 0.0.3
Summary: Feature selection for deep learning models.
Home-page: https://github.com/icc2115/dl-selection/
Author: Ian Covert
Author-email: icovert@cs.washington.edu
License: UNKNOWN
Platform: UNKNOWN
Classifier: Programming Language :: Python :: 3
Classifier: License :: OSI Approved :: MIT License
Classifier: Operating System :: OS Independent
Classifier: Intended Audience :: Science/Research
Classifier: Topic :: Scientific/Engineering
Requires-Python: >=3.6
Requires-Dist: numpy
Requires-Dist: torch
